scratchtrend/__init__.py
scratchtrend/_get.py
scratchtrend/select.py
scratchtrend-0.3.dist-info/LICENCE
scratchtrend-0.3.dist-info/METADATA
scratchtrend-0.3.dist-info/WHEEL
scratchtrend-0.3.dist-info/top_level.txt
scratchtrend-0.3.dist-info/RECORD
