Metadata-Version: 2.1
Name: scratchtrend
Version: 0.3
Summary: ScratchTrend: Get Popular Projects from scratch
Home-page: https://github.com/henji243/ScratchTrend
Download-URL: https://github.com/henji243/ScratchTrend
Author: ujex_256(henji243)
Maintainer: ujex_256(henji243)
License: MIT
Classifier: License :: OSI Approved :: MIT License
Classifier: Natural Language :: Japanese
Classifier: Natural Language :: English
Classifier: Operating System :: Microsoft :: Windows
Classifier: Programming Language :: Python :: 3
Classifier: Programming Language :: Python :: 3 :: Only
Classifier: Topic :: Internet
Requires-Python: >=3.6
License-File: LICENCE
Requires-Dist: selenium (>=4.3.0)
Requires-Dist: beautifulsoup4 (>=4.10.0)
